pupil_labs/neon_recording/__init__.py
pupil_labs/neon_recording/calib.py
pupil_labs/neon_recording/constants.py
pupil_labs/neon_recording/neon_recording.py
pupil_labs/neon_recording/py.typed
pupil_labs/neon_recording/sample.py
pupil_labs/neon_recording/utils.py
pupil_labs/neon_recording/timeseries/__init__.py
pupil_labs/neon_recording/timeseries/array_record.py
pupil_labs/neon_recording/timeseries/blinks.py
pupil_labs/neon_recording/timeseries/events.py
pupil_labs/neon_recording/timeseries/eyeball.py
pupil_labs/neon_recording/timeseries/eyelid.py
pupil_labs/neon_recording/timeseries/fixations.py
pupil_labs/neon_recording/timeseries/gaze.py
pupil_labs/neon_recording/timeseries/pupil.py
pupil_labs/neon_recording/timeseries/saccades.py
pupil_labs/neon_recording/timeseries/timeseries.py
pupil_labs/neon_recording/timeseries/worn.py
pupil_labs/neon_recording/timeseries/av/__init__.py
pupil_labs/neon_recording/timeseries/av/audio.py
pupil_labs/neon_recording/timeseries/av/base_av.py
pupil_labs/neon_recording/timeseries/av/video.py
pupil_labs/neon_recording/timeseries/imu/__init__.py
pupil_labs/neon_recording/timeseries/imu/imu_pb2.py
pupil_labs/neon_recording/timeseries/imu/imu_timeseries.py
pupil_labs_neon_recording-2.0.0.dist-info/METADATA
pupil_labs_neon_recording-2.0.0.dist-info/WHEEL
pupil_labs_neon_recording-2.0.0.dist-info/licenses/LICENSE
pupil_labs_neon_recording-2.0.0.dist-info/RECORD
