Metadata-Version: 2.4
Name: pupil-labs-neon-recording
Version: 2.0.0
Summary: Functionality for loading Neon recordings in native recording format
Project-URL: Homepage, https://pupil-labs.github.io/pl-neon-recording
Project-URL: Documentation, https://pupil-labs.github.io/pl-neon-recording
Project-URL: Repository, https://github.com/pupil-labs/pl-neon-recording
Project-URL: Issues, https://github.com/pupil-labs/pl-neon-recording/issues
Author-email: Pupil Labs GmbH <info@pupil-labs.com>
License: MIT
License-File: LICENSE
Classifier: Intended Audience :: Developers
Classifier: Programming Language :: Python
Classifier: Programming Language :: Python :: 3
Classifier: Programming Language :: Python :: 3.10
Classifier: Programming Language :: Python :: 3.11
Classifier: Programming Language :: Python :: 3.12
Classifier: Programming Language :: Python :: 3.13
Classifier: Topic :: Software Development :: Libraries :: Python Modules
Requires-Python: <4.0,>=3.10
Requires-Dist: numpy
Requires-Dist: pandas>=2.2.3
Requires-Dist: protobuf
Requires-Dist: pupil-labs-video>=1.0.5
Requires-Dist: scipy
Requires-Dist: universal-pathlib
Provides-Extra: examples
Requires-Dist: opencv-python; extra == 'examples'
Requires-Dist: pandas; extra == 'examples'
Requires-Dist: tqdm; extra == 'examples'
